zapcap_mcp_server/__init__.py
zapcap_mcp_server/server.py
zapcap_mcp_server-0.1.8.dist-info/licenses/LICENSE
zapcap_mcp_server-0.1.8.dist-info/METADATA
zapcap_mcp_server-0.1.8.dist-info/WHEEL
zapcap_mcp_server-0.1.8.dist-info/entry_points.txt
zapcap_mcp_server-0.1.8.dist-info/top_level.txt
zapcap_mcp_server-0.1.8.dist-info/RECORD
