Metadata-Version: 2.4
Name: zapcap-mcp-server
Version: 0.1.8
Summary: MCP server for ZapCap.ai video processing and caption generation
Requires-Python: >=3.13
License-File: LICENSE
Requires-Dist: httpx>=0.28.1
Requires-Dist: mcp[cli]>=1.10.1
Requires-Dist: pydantic>=2.11.7
Dynamic: license-file
